netcup_dns/__init__.py
netcup_dns/datetime_util.py
netcup_dns/exception.py
netcup_dns/main.py
netcup_dns/print_util.py
netcup_dns/record_dst_cache.py
netcup_dns/union.py
netcup_dns-0.3.1.dist-info/licenses/LICENSE
netcup_dns-0.3.1.dist-info/METADATA
netcup_dns-0.3.1.dist-info/WHEEL
netcup_dns-0.3.1.dist-info/entry_points.txt
netcup_dns-0.3.1.dist-info/top_level.txt
netcup_dns-0.3.1.dist-info/RECORD
