Metadata-Version: 2.4
Name: netcup-dns
Version: 0.3.1
Summary: Update DNS records with your current external IP address using the netcup DNS API.
Home-page: https://codeberg.org/privacy1st/netcup-dns
Author: Daniel Langbein
Author-email: daniel@systemli.org
Project-URL: Bug Tracker, https://codeberg.org/privacy1st/netcup-dns/issues
Classifier: Development Status :: 4 - Beta
Classifier: Programming Language :: Python :: 3
Classifier: License :: OSI Approved :: MIT License
Classifier: Operating System :: Unix
Requires-Python: >=3.10.0
License-File: LICENSE
Dynamic: license-file
